{
  "ask": 169.2,
  "askSize": 3,
  "averageDailyVolume10Day": 641870,
  "averageDailyVolume3Month": 647088,
  "bid": 168.54,
  "bidSize": 1,
  "corporateActions": [],
  "cryptoTradeable": false,
  "currency": "USD",
  "customPriceAlertConfidence": "HIGH",
  "dividendYield": 0.79,
  "epsTrailingTwelveMonths": 9.095911,
  "esgPopulated": false,
  "exchange": "PCX",
  "exchangeDataDelayedBy": 0,
  "exchangeTimezoneName": "America/New_York",
  "exchangeTimezoneShortName": "EDT",
  "fiftyDayAverage": 159.0942,
  "fiftyDayAverageChange": 9.785812,
  "fiftyDayAverageChangePercent": 0.06150955,
  "fiftyTwoWeekChangePercent": 46.393894,
  "fiftyTwoWeekHigh": 189.23,
  "fiftyTwoWeekHighChange": -20.34999,
  "fiftyTwoWeekHighChangePercent": -0.10754104,
  "fiftyTwoWeekLow": 92.66,
  "fiftyTwoWeekLowChange": 76.22,
  "fiftyTwoWeekLowChangePercent": 0.8225771,
  "fiftyTwoWeekRange": "92.66 - 189.23",
  "firstTradeDateMilliseconds": 1227105000000,
  "fullExchangeName": "NYSEArca",
  "gmtOffSetMilliseconds": -14400000,
  "hasPrePostMarketData": true,
  "language": "en-US",
  "longName": "Direxion Daily Financial Bull 3X Shares",
  "market": "us_market",
  "marketState": "CLOSED",
  "messageBoardId": "finmb_51234518",
  "netAssets": 2444669440.0,
  "netExpenseRatio": 0.89,
  "postMarketChange": -0.130005,
  "postMarketChangePercent": -0.0769806,
  "postMarketPrice": 168.75,
  "postMarketTime": 1752882866,
  "priceHint": 2,
  "quoteSourceName": "Nasdaq Real Time Price",
  "quoteType": "ETF",
  "region": "US",
  "regularMarketChange": 0.180008,
  "regularMarketChangePercent": 0.106703,
  "regularMarketDayHigh": 169.94,
  "regularMarketDayLow": 168.04,
  "regularMarketDayRange": "168.04 - 169.94",
  "regularMarketOpen": 169.5,
  "regularMarketPreviousClose": 168.7,
  "regularMarketPrice": 168.88,
  "regularMarketTime": 1752868800,
  "regularMarketVolume": 413560,
  "shortName": "Direxion Financial Bull 3X Shar",
  "sourceInterval": 15,
  "symbol": "FAS",
  "tradeable": false,
  "trailingAnnualDividendRate": 0.0,
  "trailingAnnualDividendYield": 0.0,
  "trailingPE": 18.566586,
  "trailingThreeMonthNavReturns": -15.12717,
  "trailingThreeMonthReturns": -15.12717,
  "triggerable": true,
  "twoHundredDayAverage": 155.59525,
  "twoHundredDayAverageChange": 13.2847595,
  "twoHundredDayAverageChangePercent": 0.08538024,
  "typeDisp": "ETF",
  "ytdReturn": 3.97099
}