{
  "ask": 18.84,
  "askSize": 8,
  "averageDailyVolume10Day": 15076020,
  "averageDailyVolume3Month": 12391173,
  "bid": 18.79,
  "bidSize": 2,
  "corporateActions": [],
  "cryptoTradeable": false,
  "currency": "USD",
  "customPriceAlertConfidence": "HIGH",
  "esgPopulated": false,
  "exchange": "NGM",
  "exchangeDataDelayedBy": 0,
  "exchangeTimezoneName": "America/New_York",
  "exchangeTimezoneShortName": "EDT",
  "fiftyDayAverage": 15.7154,
  "fiftyDayAverageChange": 3.0945997,
  "fiftyDayAverageChangePercent": 0.19691512,
  "fiftyTwoWeekChangePercent": -28.31555,
  "fiftyTwoWeekHigh": 31.18,
  "fiftyTwoWeekHighChange": -12.370001,
  "fiftyTwoWeekHighChangePercent": -0.3967287,
  "fiftyTwoWeekLow": 10.99,
  "fiftyTwoWeekLowChange": 7.8199997,
  "fiftyTwoWeekLowChangePercent": 0.71155596,
  "fiftyTwoWeekRange": "10.99 - 31.18",
  "firstTradeDateMilliseconds": 1721741400000,
  "fullExchangeName": "NasdaqGM",
  "gmtOffSetMilliseconds": -14400000,
  "hasPrePostMarketData": true,
  "ipoExpectedDate": "2024-07-23",
  "language": "en-US",
  "longName": "iShares Ethereum Trust ETF",
  "market": "us_market",
  "marketState": "CLOSED",
  "messageBoardId": "finmb_1888592120",
  "netAssets": 3583032830.0,
  "netExpenseRatio": 0.25,
  "postMarketChange": 0.18990135,
  "postMarketChangePercent": 1.0095766,
  "postMarketPrice": 18.9999,
  "postMarketTime": 1749254380,
  "priceHint": 2,
  "quoteSourceName": "Delayed Quote",
  "quoteType": "ETF",
  "region": "US",
  "regularMarketChange": -0.34,
  "regularMarketChangePercent": -1.77546,
  "regularMarketDayHigh": 19.19,
  "regularMarketDayLow": 18.8003,
  "regularMarketDayRange": "18.8003 - 19.19",
  "regularMarketOpen": 18.8265,
  "regularMarketPreviousClose": 19.15,
  "regularMarketPrice": 18.81,
  "regularMarketTime": 1749240001,
  "regularMarketVolume": 11653608,
  "shortName": "iShares Ethereum Trust - iShare",
  "sourceInterval": 15,
  "symbol": "ETHA",
  "tradeable": false,
  "trailingThreeMonthNavReturns": 16.4297,
  "trailingThreeMonthReturns": 16.4297,
  "triggerable": true,
  "twoHundredDayAverage": 19.896275,
  "twoHundredDayAverageChange": -1.0862751,
  "twoHundredDayAverageChangePercent": -0.05459691,
  "typeDisp": "ETF",
  "ytdReturn": -22.98707
}