{
  "ask": 86.31,
  "askSize": 2,
  "averageDailyVolume10Day": 39310100,
  "averageDailyVolume3Month": 42397585,
  "bid": 86.25,
  "bidSize": 15,
  "bookValue": 148.865,
  "corporateActions": [],
  "cryptoTradeable": false,
  "currency": "USD",
  "customPriceAlertConfidence": "HIGH",
  "dividendDate": 1496793600,
  "dividendYield": 4.39,
  "epsForward": -0.02,
  "epsTrailingTwelveMonths": -12.586,
  "esgPopulated": false,
  "exchange": "NGM",
  "exchangeDataDelayedBy": 0,
  "exchangeTimezoneName": "America/New_York",
  "exchangeTimezoneShortName": "EDT",
  "fiftyDayAverage": 87.0526,
  "fiftyDayAverageChange": -0.7225952,
  "fiftyDayAverageChangePercent": -0.008300674,
  "fiftyTwoWeekChangePercent": -7.8950167,
  "fiftyTwoWeekHigh": 101.64,
  "fiftyTwoWeekHighChange": -15.309998,
  "fiftyTwoWeekHighChangePercent": -0.15062965,
  "fiftyTwoWeekLow": 83.3,
  "fiftyTwoWeekLowChange": 3.0299988,
  "fiftyTwoWeekLowChangePercent": 0.036374535,
  "fiftyTwoWeekRange": "83.3 - 101.64",
  "financialCurrency": "USD",
  "firstTradeDateMilliseconds": 1028035800000,
  "forwardPE": -4316.5,
  "fullExchangeName": "NasdaqGM",
  "gmtOffSetMilliseconds": -14400000,
  "hasPrePostMarketData": true,
  "language": "en-US",
  "longName": "iShares 20+ Year Treasury Bond ETF",
  "market": "us_market",
  "marketCap": 9470401536,
  "marketState": "CLOSED",
  "messageBoardId": "finmb_8797414",
  "netAssets": 50897134000.0,
  "netExpenseRatio": 0.15,
  "postMarketChange": -0.159302,
  "postMarketChangePercent": -0.184527,
  "postMarketPrice": 86.1707,
  "postMarketTime": 1749859176,
  "priceHint": 2,
  "priceToBook": 0.5799214,
  "quoteSourceName": "Nasdaq Real Time Price",
  "quoteType": "ETF",
  "region": "US",
  "regularMarketChange": -0.839996,
  "regularMarketChangePercent": -0.96363,
  "regularMarketDayHigh": 86.875,
  "regularMarketDayLow": 85.775,
  "regularMarketDayRange": "85.775 - 86.875",
  "regularMarketOpen": 86.73,
  "regularMarketPreviousClose": 87.17,
  "regularMarketPrice": 86.33,
  "regularMarketTime": 1749844800,
  "regularMarketVolume": 49120795,
  "sharesOutstanding": 109700000,
  "shortName": "iShares 20+ Year Treasury Bond ",
  "sourceInterval": 15,
  "symbol": "TLT",
  "tradeable": false,
  "trailingAnnualDividendRate": 2.152,
  "trailingAnnualDividendYield": 0.024687393,
  "trailingThreeMonthNavReturns": -5.71257,
  "trailingThreeMonthReturns": -5.71257,
  "triggerable": true,
  "twoHundredDayAverage": 90.7205,
  "twoHundredDayAverageChange": -4.3904953,
  "twoHundredDayAverageChangePercent": -0.048395846,
  "typeDisp": "ETF",
  "ytdReturn": 0.02071
}