{
  "ask": 26.16,
  "askSize": 114,
  "averageDailyVolume10Day": 14486680,
  "averageDailyVolume3Month": 18802057,
  "bid": 26.15,
  "bidSize": 1019,
  "corporateActions": [],
  "cryptoTradeable": false,
  "currency": "USD",
  "customPriceAlertConfidence": "HIGH",
  "dividendYield": 4.03,
  "epsTrailingTwelveMonths": 1.6646154,
  "esgPopulated": false,
  "exchange": "PCX",
  "exchangeDataDelayedBy": 0,
  "exchangeTimezoneName": "America/New_York",
  "exchangeTimezoneShortName": "EDT",
  "fiftyDayAverage": 26.197,
  "fiftyDayAverageChange": -0.027000427,
  "fiftyDayAverageChangePercent": -0.0010306686,
  "fiftyTwoWeekChangePercent": 0.47351122,
  "fiftyTwoWeekHigh": 29.72,
  "fiftyTwoWeekHighChange": -3.5499992,
  "fiftyTwoWeekHighChangePercent": -0.11944816,
  "fiftyTwoWeekLow": 23.87,
  "fiftyTwoWeekLowChange": 2.2999992,
  "fiftyTwoWeekLowChangePercent": 0.09635522,
  "fiftyTwoWeekRange": "23.87 - 29.72",
  "firstTradeDateMilliseconds": 1319117400000,
  "fullExchangeName": "NYSEArca",
  "gmtOffSetMilliseconds": -14400000,
  "hasPrePostMarketData": true,
  "language": "en-US",
  "longName": "Schwab U.S. Dividend Equity ETF",
  "market": "us_market",
  "marketState": "CLOSED",
  "messageBoardId": "finmb_141947998",
  "netAssets": 66914001000.0,
  "netExpenseRatio": 0.06,
  "postMarketChange": 0.0,
  "postMarketChangePercent": 0.0,
  "postMarketPrice": 26.17,
  "postMarketTime": 1748649585,
  "priceHint": 2,
  "quoteSourceName": "Delayed Quote",
  "quoteType": "ETF",
  "region": "US",
  "regularMarketChange": -0.0200005,
  "regularMarketChangePercent": -0.0763668,
  "regularMarketDayHigh": 26.27,
  "regularMarketDayLow": 25.99,
  "regularMarketDayRange": "25.99 - 26.27",
  "regularMarketOpen": 26.12,
  "regularMarketPreviousClose": 26.19,
  "regularMarketPrice": 26.17,
  "regularMarketTime": 1748635200,
  "regularMarketVolume": 14722426,
  "shortName": "Schwab US Dividend Equity ETF",
  "sourceInterval": 15,
  "symbol": "SCHD",
  "tradeable": false,
  "trailingAnnualDividendRate": 0.0,
  "trailingAnnualDividendYield": 0.0,
  "trailingPE": 15.72135,
  "trailingThreeMonthNavReturns": -6.3918,
  "trailingThreeMonthReturns": -6.3918,
  "triggerable": true,
  "twoHundredDayAverage": 27.613934,
  "twoHundredDayAverageChange": -1.4439335,
  "twoHundredDayAverageChangePercent": -0.052290034,
  "typeDisp": "ETF",
  "ytdReturn": -4.5745
}